[
  {
    "name": "三井住友NL｜セブン-イレブン スマホのタッチ決済で+9.5%（最大10%のうちVポイント分）※会員コード提示0.5%別枠",
    "brand": "三井住友カードゴールドNL",
    "type": "add",
    "bonus": 9.5,
    "store": "セブン",
    "category": "convenience_store",
    "start": "2024-10-15",
    "end": "2025-12-31"
  },
  {
    "name": "三井住友NL｜ファミリーマート 対象のコンビニ最大7%のVポイント（スマホのタッチ決済）",
    "brand": "三井住友カードゴールドNL",
    "type": "add",
    "bonus": 6.0,
    "store": "ファミリーマート",
    "category": "convenience_store",
    "start": "2024-01-01",
    "end": "2025-12-31"
  },
  {
    "name": "三井住友NL｜ローソン 対象のコンビニ最大7%のVポイント（スマホのタッチ決済）",
    "brand": "三井住友カードゴールドNL",
    "type": "add",
    "bonus": 6.0,
    "store": "ローソン",
    "category": "convenience_store",
    "start": "2024-01-01",
    "end": "2025-12-31"
  },
  {
    "name": "三菱UFJカード｜松屋（券売機・セルフレジ）+6.0%（7%還元相当）",
    "brand": "三菱UFJカード",
    "type": "add",
    "bonus": 6.0,
    "store": "松屋",
    "category": "restaurant",
    "start": "2025-01-01",
    "end": "2025-12-31"
  },
  {
    "name": "三菱UFJカード｜松のや +6.0%（7%還元相当）",
    "brand": "三菱UFJカード",
    "type": "add",
    "bonus": 6.0,
    "store": "松のや",
    "category": "restaurant",
    "start": "2025-01-01",
    "end": "2025-12-31"
  },
  {
    "name": "三菱UFJカード｜マイカリー食堂 +6.0%（7%還元相当）",
    "brand": "三菱UFJカード",
    "type": "add",
    "bonus": 6.0,
    "store": "マイカリー食堂",
    "category": "restaurant",
    "start": "2025-01-01",
    "end": "2025-12-31"
  },
  {
    "name": "三菱UFJカード｜OK（オーケー） +6.0%（7%還元相当）",
    "brand": "三菱UFJカード",
    "type": "add",
    "bonus": 6.0,
    "store": "オーケー",
    "category": "supermarket",
    "start": "2025-01-01",
    "end": "2025-12-31"
  },
  {
    "name": "三菱UFJカード｜東急ストア +6.0%（7%還元相当）",
    "brand": "三菱UFJカード",
    "type": "add",
    "bonus": 6.0,
    "store": "東急ストア",
    "category": "supermarket",
    "start": "2025-01-01",
    "end": "2025-12-31"
  },
  {
    "name": "三菱UFJカード｜東武ストア +6.0%（7%還元相当）",
    "brand": "三菱UFJカード",
    "type": "add",
    "bonus": 6.0,
    "store": "東武ストア",
    "category": "supermarket",
    "start": "2025-01-01",
    "end": "2025-12-31"
  },
  {
    "name": "三菱UFJカード｜オオゼキ +6.0%（7%還元相当）",
    "brand": "三菱UFJカード",
    "type": "add",
    "bonus": 6.0,
    "store": "オオゼキ",
    "category": "supermarket",
    "start": "2025-01-01",
    "end": "2025-12-31"
  },
  {
    "name": "三菱UFJカード｜アオキスーパー +6.0%（7%還元相当）",
    "brand": "三菱UFJカード",
    "type": "add",
    "bonus": 6.0,
    "store": "アオキスーパー",
    "category": "supermarket",
    "start": "2025-01-01",
    "end": "2025-12-31"
  },
  {
    "name": "三菱UFJカード｜サンリブ +6.0%（7%還元相当）",
    "brand": "三菱UFJカード",
    "type": "add",
    "bonus": 6.0,
    "store": "サンリブ",
    "category": "supermarket",
    "start": "2025-01-01",
    "end": "2025-12-31"
  },
  {
    "name": "三菱UFJカード｜三和/フードワン +6.0%（7%還元相当）",
    "brand": "三菱UFJカード",
    "type": "add",
    "bonus": 6.0,
    "store": "三和",
    "category": "supermarket",
    "start": "2025-01-01",
    "end": "2025-12-31"
  },
  {
    "name": "JQエポスゴールド｜選べるポイントアップショップ（例：吉野家/すき家/松屋等を登録した場合）倍率×3（登録時のみ/3ヵ月固定）",
    "brand": "JQエポスゴールド",
    "type": "multi",
    "multiplier": 3.0,
    "category": "restaurant",
    "start": "2025-02-03",
    "end": "2026-03-31"
  },
  {
    "name": "JRE CARD｜JRE CARD優待店 3.5%（内訳: 優待店3%+請求時加算0.5%）",
    "brand": "JREカード",
    "type": "add",
    "bonus": 2.5,
    "category": "supermarket",
    "start": "2025-01-01",
    "end": "2025-12-31"
  },
  {
    "name": "JCB｜スターバックス（スタバカードオンライン入金/オートチャージ）例: +4.5%（カード種別により倍率。要調整）",
    "brand": "JCBカード",
    "type": "add",
    "bonus": 4.5,
    "store": "スターバックス",
    "category": "cafe",
    "start": "2025-01-31",
    "end": "2026-03-31"
  },
  {
    "name": "（例）JQエポスG｜吉野家 選べるポイントアップ×3（登録時）",
    "brand": "JQエポスゴールド",
    "type": "multi",
    "category": "restaurant",
    "store": "吉野家",
    "start": "2025-01-01",
    "end": "2025-12-31",
    "multiplier": 3.0
  },
  {
    "name": "（例）JQエポスG｜すき家 選べるポイントアップ×3（登録時）",
    "brand": "JQエポスゴールド",
    "type": "multi",
    "category": "restaurant",
    "store": "すき家",
    "start": "2025-01-01",
    "end": "2025-12-31",
    "multiplier": 3.0
  },
  {
    "name": "（例）ウエルシア系優遇｜ウエルシア（ウエルシアカード想定）",
    "brand": "ウエルシアカード",
    "type": "add",
    "category": "drugstore",
    "store": "ウエルシア",
    "start": "2025-01-01",
    "end": "2025-12-31",
    "bonus": 0.5
  },
  {
    "name": "（例）ウエルシア系優遇｜マツモトキヨシ（ウエルシアカード想定）",
    "brand": "ウエルシアカード",
    "type": "add",
    "category": "drugstore",
    "store": "マツモトキヨシ",
    "start": "2025-01-01",
    "end": "2025-12-31",
    "bonus": 0.5
  },
  {
    "name": "（例）ウエルシア系優遇｜ココカラファイン（ウエルシアカード想定）",
    "brand": "ウエルシアカード",
    "type": "add",
    "category": "drugstore",
    "store": "ココカラファイン",
    "start": "2025-01-01",
    "end": "2025-12-31",
    "bonus": 0.5
  },
  {
    "name": "（例）ウエルシア系優遇｜ツルハ（ウエルシアカード想定）",
    "brand": "ウエルシアカード",
    "type": "add",
    "category": "drugstore",
    "store": "ツルハ",
    "start": "2025-01-01",
    "end": "2025-12-31",
    "bonus": 0.5
  },
  {
    "name": "（例）ウエルシア系優遇｜スギ薬局（ウエルシアカード想定）",
    "brand": "ウエルシアカード",
    "type": "add",
    "category": "drugstore",
    "store": "スギ薬局",
    "start": "2025-01-01",
    "end": "2025-12-31",
    "bonus": 0.5
  },
  {
    "name": "（例）ウエルシア系優遇｜サンドラッグ（ウエルシアカード想定）",
    "brand": "ウエルシアカード",
    "type": "add",
    "category": "drugstore",
    "store": "サンドラッグ",
    "start": "2025-01-01",
    "end": "2025-12-31",
    "bonus": 0.5
  },
  {
    "name": "（例）ウエルシア系優遇｜クリエイトSD（ウエルシアカード想定）",
    "brand": "ウエルシアカード",
    "type": "add",
    "category": "drugstore",
    "store": "クリエイトSD",
    "start": "2025-01-01",
    "end": "2025-12-31",
    "bonus": 0.5
  },
  {
    "name": "（例）ウエルシア系優遇｜ドラッグセイムス（ウエルシアカード想定）",
    "brand": "ウエルシアカード",
    "type": "add",
    "category": "drugstore",
    "store": "ドラッグセイムス",
    "start": "2025-01-01",
    "end": "2025-12-31",
    "bonus": 0.5
  },
  {
    "name": "（例）QR週末+1%｜ウエルシア（編集して実施期間・上限を反映）",
    "brand": "PayPay",
    "type": "add",
    "category": "drugstore",
    "store": "ウエルシア",
    "start": "2025-01-01",
    "end": "2025-12-31",
    "bonus": 1.0,
    "cap": "月1,000ポイント"
  },
  {
    "name": "（例）QR週末+1%｜マツモトキヨシ（編集して実施期間・上限を反映）",
    "brand": "PayPay",
    "type": "add",
    "category": "drugstore",
    "store": "マツモトキヨシ",
    "start": "2025-01-01",
    "end": "2025-12-31",
    "bonus": 1.0,
    "cap": "月1,000ポイント"
  },
  {
    "name": "（例）QR週末+1%｜ココカラファイン（編集して実施期間・上限を反映）",
    "brand": "PayPay",
    "type": "add",
    "category": "drugstore",
    "store": "ココカラファイン",
    "start": "2025-01-01",
    "end": "2025-12-31",
    "bonus": 1.0,
    "cap": "月1,000ポイント"
  },
  {
    "name": "（例）QR週末+1%｜ツルハ（編集して実施期間・上限を反映）",
    "brand": "PayPay",
    "type": "add",
    "category": "drugstore",
    "store": "ツルハ",
    "start": "2025-01-01",
    "end": "2025-12-31",
    "bonus": 1.0,
    "cap": "月1,000ポイント"
  },
  {
    "name": "（例）QR週末+1%｜スギ薬局（編集して実施期間・上限を反映）",
    "brand": "PayPay",
    "type": "add",
    "category": "drugstore",
    "store": "スギ薬局",
    "start": "2025-01-01",
    "end": "2025-12-31",
    "bonus": 1.0,
    "cap": "月1,000ポイント"
  },
  {
    "name": "（例）QR週末+1%｜サンドラッグ（編集して実施期間・上限を反映）",
    "brand": "PayPay",
    "type": "add",
    "category": "drugstore",
    "store": "サンドラッグ",
    "start": "2025-01-01",
    "end": "2025-12-31",
    "bonus": 1.0,
    "cap": "月1,000ポイント"
  },
  {
    "name": "（例）QR週末+1%｜クリエイトSD（編集して実施期間・上限を反映）",
    "brand": "PayPay",
    "type": "add",
    "category": "drugstore",
    "store": "クリエイトSD",
    "start": "2025-01-01",
    "end": "2025-12-31",
    "bonus": 1.0,
    "cap": "月1,000ポイント"
  },
  {
    "name": "（例）QR週末+1%｜ドラッグセイムス（編集して実施期間・上限を反映）",
    "brand": "PayPay",
    "type": "add",
    "category": "drugstore",
    "store": "ドラッグセイムス",
    "start": "2025-01-01",
    "end": "2025-12-31",
    "bonus": 1.0,
    "cap": "月1,000ポイント"
  },
  {
    "name": "（例）JQエポスG｜イオン 選べるポイントアップ×3（登録時）",
    "brand": "JQエポスゴールド",
    "type": "multi",
    "category": "supermarket",
    "store": "イオン",
    "start": "2025-01-01",
    "end": "2025-12-31",
    "multiplier": 3.0
  },
  {
    "name": "（例）JQエポスG｜ライフ 選べるポイントアップ×3（登録時）",
    "brand": "JQエポスゴールド",
    "type": "multi",
    "category": "supermarket",
    "store": "ライフ",
    "start": "2025-01-01",
    "end": "2025-12-31",
    "multiplier": 3.0
  },
  {
    "name": "（例）JQエポスG｜西友 選べるポイントアップ×3（登録時）",
    "brand": "JQエポスゴールド",
    "type": "multi",
    "category": "supermarket",
    "store": "西友",
    "start": "2025-01-01",
    "end": "2025-12-31",
    "multiplier": 3.0
  },
  {
    "name": "（例）JQエポスG｜イトーヨーカドー 選べるポイントアップ×3（登録時）",
    "brand": "JQエポスゴールド",
    "type": "multi",
    "category": "supermarket",
    "store": "イトーヨーカドー",
    "start": "2025-01-01",
    "end": "2025-12-31",
    "multiplier": 3.0
  },
  {
    "name": "（例）JQエポスG｜成城石井 選べるポイントアップ×3（登録時）",
    "brand": "JQエポスゴールド",
    "type": "multi",
    "category": "supermarket",
    "store": "成城石井",
    "start": "2025-01-01",
    "end": "2025-12-31",
    "multiplier": 3.0
  },
  {
    "name": "（例）三菱UFJ｜オーケー +6.0%（要公式条件確認）",
    "brand": "三菱UFJカード",
    "type": "add",
    "category": "supermarket",
    "store": "オーケー",
    "start": "2025-01-01",
    "end": "2025-12-31",
    "bonus": 6.0
  },
  {
    "name": "（例）三菱UFJ｜東急ストア +6.0%（要公式条件確認）",
    "brand": "三菱UFJカード",
    "type": "add",
    "category": "supermarket",
    "store": "東急ストア",
    "start": "2025-01-01",
    "end": "2025-12-31",
    "bonus": 6.0
  },
  {
    "name": "（例）三菱UFJ｜東武ストア +6.0%（要公式条件確認）",
    "brand": "三菱UFJカード",
    "type": "add",
    "category": "supermarket",
    "store": "東武ストア",
    "start": "2025-01-01",
    "end": "2025-12-31",
    "bonus": 6.0
  },
  {
    "name": "（例）三菱UFJ｜オオゼキ +6.0%（要公式条件確認）",
    "brand": "三菱UFJカード",
    "type": "add",
    "category": "supermarket",
    "store": "オオゼキ",
    "start": "2025-01-01",
    "end": "2025-12-31",
    "bonus": 6.0
  },
  {
    "name": "（例）JQエポスG｜ベルク 選べるポイントアップ×3（登録時）",
    "brand": "JQエポスゴールド",
    "type": "multi",
    "category": "supermarket",
    "store": "ベルク",
    "start": "2025-01-01",
    "end": "2025-12-31",
    "multiplier": 3.0
  },
  {
    "name": "（例）JQエポスG｜ヤオコー 選べるポイントアップ×3（登録時）",
    "brand": "JQエポスゴールド",
    "type": "multi",
    "category": "supermarket",
    "store": "ヤオコー",
    "start": "2025-01-01",
    "end": "2025-12-31",
    "multiplier": 3.0
  },
  {
    "name": "（例）JQエポスG｜サミット 選べるポイントアップ×3（登録時）",
    "brand": "JQエポスゴールド",
    "type": "multi",
    "category": "supermarket",
    "store": "サミット",
    "start": "2025-01-01",
    "end": "2025-12-31",
    "multiplier": 3.0
  }
]